Workbook

Sheet Read me
A1: Marginwise Instagram content calendar: 14 Oct to 15 Nov 2026
A3: Five weeks, 20 posts: 3 reels and 1 carousel a week, plus Stories on 4 days. Built from marginwise/instagram-playbook.md.
A4: Tabs
A5: Calendar: every post with hook, outline, caption, CTA keyword and lead magnet. Fill the yellow columns after posting.
A6: Stories: the weekly Stories rhythm.
A7: Filming batches: what to film in each session so you are never filming the night before.
A8: Weekly review: totals per week, calculated from the Calendar tab.
A9: Setup before 14 Oct: the checklist to finish before the first post.
A10: Rules
A11: All posts go out at 19:30 IST. That is 10:00 US Eastern and 15:00 UK until the clocks change (UK 25 Oct, US 1 Nov); the Calendar tab shows the exact local times for each date.
A12: No holiday greetings, memes or office posts. They underperformed for every competitor reviewed.
A13: Replace [Brand] placeholders with public pages only. Keep the tone constructive and keep logos out of thumbnails.
... A16: Yellow cells are for you to fill in after posting (link, reach, saves, shares, DMs, calls).

Sheet Calendar
A1: Week | B1: Date | C1: Day | D1: IST | E1: US Eastern | F1: UK | G1: Format | H1: Pillar | I1: Market | J1: Hook (on screen) | K1: Outline | L1: Caption | M1: CTA keyword | N1: Lead magnet | O1: Trial Reel first? | P1: Pin? | Q1: Filming batch | R1: Status | S1: Post link | T1: Reach | U1: Saves | V1: Shares | W1: Comments | X1: DMs | Y1: Calls booked
A2: 1 | B2: 46309 | C2: Wed | D2: 19:30 | E2: 10:00 | F2: 15:00 | G2: Reel (60s) | H2: Proof and trust | I2: Both | J2: Every agency sells you ROAS. I sell you margin. | K2: 1) Who I am: 10 years building D2C, omnichannel and loyalty products. 2) The four services in one line each. 3) Who it is not for: pre-launch ideas, single theme tweaks, guaranteed-results deals. 4) How the free 30-min call works and what you leave with. | L2: Most agencies report ROAS. We report what you keep. Marginwise runs CRO, performance marketing, UX and app development for D2C and Shopify brands in India, the US and the UK. Every engagement starts with a free 30-minute call: you leave with your top three leaks and a written summary. Comment AUDIT and I will send you a 2-minute teardown of your store. #d2c #shopify #ecommercegrowth | M2: AUDIT | N2: Free 2-min teardown (manual) | O2: No | P2: Yes | Q2: Batch 1 | R2: Planned
A3: 1 | B3: 46311 | C3: Fri | D3: 19:30 | E3: 10:00 | F3: 15:00 | G3: Reel (45s) | H3: Margin math | I3: Intl | J3: Your ROAS says 3x. Your bank account disagrees. | K3: Show 3x ROAS on screen. Remove over-attribution, returns, COGS, shipping, payment fees one by one. Land on contribution after ads. End: track contribution margin per order, not ROAS. | L3: ROAS is not profit. Here is what a 3x ROAS can actually leave you with once over-attribution, returns, product cost, shipping and fees come out. Comment PROFIT and I will send you the calculator to run it on your own numbers. #shopify #metaads #dtc | M3: PROFIT | N3: marginwise-profit-calculator-usd.xlsx | O3: Yes | P3: Yes | Q3: Batch 1 | R3: Planned
A4: 1 | B4: 46312 | C4: Sat | D4: 19:30 | E4: 10:00 | F4: 15:00 | G4: Carousel (7 slides) | H4: Margin math | I4: Both | J4: Where D2C revenue leaks: 4 numbers every founder should know | K4: S1 hook. S2 70.22% of carts abandoned (Baymard). S3 35% conversion gain from better checkout design (Baymard). S4 8.4% more conversions from 0.1s faster mobile (Deloitte/Google). S5 26% RTO on COD vs under 2% prepaid (Shipway FY25). S6 what to fix first. S7 CTA. | L4: Four published numbers that explain where most D2C stores lose revenue, and what to fix first for each. Sources on every slide. Save this for your next growth review. Comment AUDIT if you want us to check your store against them. #ecommerce #cro #d2cbrands | M4: AUDIT | N4: Free 2-min teardown (manual) | O4: No | P4: No | Q4: Design | R4: Planned
A5: 1 | B5: 46313 | C5: Sun | D5: 19:30 | E5: 10:00 | F5: 15:00 | G5: Reel (50s) | H5: COD/RTO | I5: India | J5: 26% of your COD orders come back. | K5: Shipway FY25: 26% RTO on COD vs under 2% prepaid. What one RTO costs: forward and return shipping, packaging, wasted ad spend. Three fixes: prepaid incentive, WhatsApp confirmation for risky COD, switch off COD only in high-RTO pin codes. | L5: Switching off COD everywhere is the wrong fix. Find the pin codes where it loses money and act only there. Comment RTO and I will send you the sheet that ranks your states and pin codes by RTO cost. #d2cindia #rto #shopifyindia | M5: RTO | N5: marginwise-rto-finder.xlsx | O5: Yes | P5: Yes | Q5: Batch 1 | R5: Planned
A6: 2 | B6: 46315 | C6: Tue | D6: 19:30 | E6: 10:00 | F6: 15:00 | G6: Reel (60s) | H6: Teardown | I6: Intl | J6: [Brand] does everything right on this page except one thing. | K6: Screen-record a well-known US/UK brand's mobile product page. Two strengths, one leak (hidden shipping cost, review placement, or slow image). What that leak costs in margin. | L6: A product page teardown with a margin lens: what converts, what leaks, and what the leak costs. Want this for your store? Comment AUDIT. #shopifycro #productpage #ecommerce | M6: AUDIT | N6: Free 2-min teardown (manual) | O6: Yes | P6: No | Q6: Batch 1 | R6: Planned
A7: 2 | B7: 46317 | C7: Thu | D7: 19:30 | E7: 10:00 | F7: 15:00 | G7: Reel (60s) | H7: Margin math | I7: India | J7: Your revenue is growing. Your profit isn't. Here's why. | K7: Break down a ₹1,000 order: GST, COGS, ad cost per order, shipping, RTO, gateway fees, discounts. Land on contribution margin per order. Investors now ask for this, not GMV. | L7: Contribution margin per order, explained with a real ₹1,000 example. Comment MARGIN and I will send you the calculator, including a what-if for pushing more buyers to prepaid. #d2cindia #unitEconomics #founders | M7: MARGIN | N7: marginwise-margin-calculator-inr.xlsx | O7: No | P7: No | Q7: Batch 1 | R7: Planned
A8: 2 | B8: 46319 | C8: Sat | D8: 19:30 | E8: 10:00 | F8: 15:00 | G8: Carousel (8 slides) | H8: Margin math | I8: India | J8: What a ₹1,000 order actually earns you | K8: One cost per slide: GST, product cost, ad cost, shipping and packaging, RTO, COD fees, gateway fees. Final slide: contribution per order and the one lever that moves it most. | L8: Line by line, what is left of a ₹1,000 order once every cost is counted. Numbers are an example store; run your own with the calculator. Comment MARGIN for the sheet. #d2cindia #ecommerceindia #margin | M8: MARGIN | N8: marginwise-margin-calculator-inr.xlsx | O8: No | P8: No | Q8: Design | R8: Planned
A9: 2 | B9: 46320 | C9: Sun | D9: 19:30 | E9: 10:00 | F9: 14:00 | G9: Reel (45s) | H9: Teardown | I9: Both | J9: Save these 5 checkout pages before you redesign yours. | K9: Five public checkouts (mix of US/UK and Indian). One thing each does well: trust badges placement, delivery date, COD/prepaid nudge, express pay, order summary clarity. | L9: Five checkouts worth studying before your next redesign, and the one thing each gets right. Save this. Comment AUDIT if you want yours reviewed. #checkout #shopify #cro | M9: AUDIT | N9: Free 2-min teardown (manual) | O9: Yes | P9: No | Q9: Batch 1 | R9: Planned
A10: 3 | B10: 46322 | C10: Tue | D10: 19:30 | E10: 10:00 | F10: 14:00 | G10: Reel (45s) | H10: CRO | I10: Intl | J10: 7 out of 10 people who add to cart never buy. | K10: Baymard: 70.22% average cart abandonment across 50 studies. Three fixable reasons: surprise costs, forced account creation, too many steps. Show one fix for each on a Shopify checkout. | L10: Cart abandonment averages 70% (Baymard Institute). Three fixes that do not need a redesign. Save this for your next checkout review. #checkout #shopifytips #ecommerce | M10: Save | N10: None | O10: Yes | P10: No | Q10: Batch 2 | R10: Planned
A11: 3 | B11: 46324 | C11: Thu | D11: 19:30 | E11: 10:00 | F11: 14:00 | G11: Reel (60s) | H11: Teardown | I11: India | J11: [Indian Brand] is losing mobile buyers here. | K11: Screen-record an Indian D2C brand's mobile product page. Two strengths, one leak (COD/prepaid messaging, delivery date clarity, size guidance). The fix. | L11: A mobile product page teardown of an Indian D2C brand, and one fix that lifts conversion without a redesign. Comment AUDIT for a teardown of your store. #d2cindia #cro #shopifyindia | M11: AUDIT | N11: Free 2-min teardown (manual) | O11: Yes | P11: No | Q11: Batch 2 | R11: Planned
A12: 3 | B12: 46326 | C12: Sat | D12: 19:30 | E12: 10:00 | F12: 14:00 | G12: Carousel (6 slides) | H12: Proof and trust | I12: Intl | J12: How a US or UK brand works with a team in India | K12: S1 hook. S2 overlap hours (your morning, our evening). S3 weekly written update, with redacted example. S4 one senior contact. S5 billing in USD/GBP, NDA, 30-day notice. S6 CTA. | L12: The three things founders worry about with an offshore team, and exactly how we handle each one. See how we work at the link in bio. #ecommerceagency #shopifyexperts #dtc | M12: Link in bio | N12: None | O12: No | P12: No | Q12: Design | R12: Planned
A13: 3 | B13: 46327 | C13: Sun | D13: 19:30 | E13: 09:00 | F13: 14:00 | G13: Reel (50s) | H13: Proof and trust | I13: Intl | J13: Why US brands are scared to hire an agency in India. | K13: Communication, time zones, quality. How each should be handled by any agency: overlap hours, weekly written update, one senior point of contact. 'Ask any agency for these three.' | L13: What to ask any offshore agency before you sign, ourselves included. Comment CHECKLIST for the full agency hiring checklist. #ecommerceagency #shopify #dtcbrands | M13: CHECKLIST | N13: marginwise-agency-checklist.pdf | O13: No | P13: No | Q13: Batch 2 | R13: Planned
... A21: 5 | B21: 46341 | C21: Sun | D21: 19:30 | E21: 09:00 | F21: 14:00 | G21: Reel (60s) | H21: Proof and trust | I21: Both | J21: I audited [N] D2C stores this month. The same 3 leaks showed up in [X] of them. | K21: Only post if the audits are real; use the actual count. Three most common leaks, anonymised. If fewer than 5 audits are done, swap for a second Indian teardown. | L21: What we keep finding when we audit D2C stores, with no names attached. Comment AUDIT to get yours. #d2c #cro #ecommercegrowth | M21: AUDIT | N21: Free 2-min teardown (manual) | O21: No | P21: No | Q21: Batch 3 | R21: Planned

Sheet Stories
A1: Day | B1: Story type | C1: What to post | D1: Sticker | E1: Why
A2: Monday | B2: Poll | C2: One question for founders, alternating markets. Examples: 'What is your COD share? Under 30% / Over 30%'; 'Do you track contribution margin weekly? Yes / No'. | D2: Poll | E2: Two-way interaction now ranks; poll answers tell you what to post next.
A3: Wednesday | B3: Behind the scenes | C3: 15 seconds from a teardown in progress: the store on screen, one thing you spotted. No client names. | D3: Question box: 'Want yours next?' | E3: Shows the work, feeds AUDIT requests.
A4: Friday | B4: Reel share | C4: Share the week's best-performing reel with a one-line takeaway. | D4: Link: marginwise.in booking | E4: Stories with link stickers are the highest-intent surface.
A5: Sunday | B5: Answer | C5: Answer one question from DMs or the question box on camera (30-45s). | D5: None | E5: Turns DMs into content and shows you reply.

Sheet Filming batches
A1: Batch | B1: Film on | C1: Posts covered | D1: What to prepare | E1: Time needed
A2: Batch 1 | B2: 46308 | C2: Founder intro; ROAS 3x; COD RTO 26%; US/UK product page teardown; ₹1,000 order margin; 5 checkout pages | D2: Pick the US/UK brand and 5 checkouts (public pages). Screen recordings done before filming. Same shirt across takes to batch-edit. | E2: 3 hours
A3: Batch 2 | B3: 46319 | C3: Cart abandonment; Indian teardown; offshore trust; email ratings; site speed; agency questions | D3: Pick the Indian brand and three order confirmation emails (your own inbox or public examples). Run PageSpeed on one public store. | E3: 3 hours
A4: Batch 3 | B4: 46333 | C4: Tariffs; GST on ads; audit roundup | D4: Count real audits done so far. If fewer than 5, film a second Indian teardown instead of the roundup. | E4: 2 hours
A5: Design | B5: 46310 | C5: All five carousels | D5: Use the same template: navy and white, one idea per slide, source line on every stat slide. Canva or Figma. | E5: 4 hours

Sheet Weekly review
A1: Week | B1: Week starting | C1: Posts planned | D1: Posts posted | E1: Reach | F1: Saves | G1: Shares | H1: Comments | I1: DMs | J1: Calls booked | K1: Shares per 1,000 reach | L1: What to change next week
A2: 1 | B2: 46307 | C2: =COUNTIF(Calendar!$A$2:$A$21,A2) -> 4 | D2: =COUNTIFS(Calendar!$A$2:$A$21,A2,Calendar!$R$2:$R$21,"Posted") -> 0 | E2: =SUMIF(Calendar!$A$2:$A$21,A2,Calendar!$T$2:$T$21) -> 0 | F2: =SUMIF(Calendar!$A$2:$A$21,A2,Calendar!$U$2:$U$21) -> 0 | G2: =SUMIF(Calendar!$A$2:$A$21,A2,Calendar!$V$2:$V$21) -> 0 | H2: =SUMIF(Calendar!$A$2:$A$21,A2,Calendar!$W$2:$W$21) -> 0 | I2: =SUMIF(Calendar!$A$2:$A$21,A2,Calendar!$X$2:$X$21) -> 0 | J2: =SUMIF(Calendar!$A$2:$A$21,A2,Calendar!$Y$2:$Y$21) -> 0 | K2: =IFERROR(G2/E2*1000,0) -> 0
A3: 2 | B3: 46314 | C3: =COUNTIF(Calendar!$A$2:$A$21,A3) -> 4 | D3: =COUNTIFS(Calendar!$A$2:$A$21,A3,Calendar!$R$2:$R$21,"Posted") -> 0 | E3: =SUMIF(Calendar!$A$2:$A$21,A3,Calendar!$T$2:$T$21) -> 0 | F3: =SUMIF(Calendar!$A$2:$A$21,A3,Calendar!$U$2:$U$21) -> 0 | G3: =SUMIF(Calendar!$A$2:$A$21,A3,Calendar!$V$2:$V$21) -> 0 | H3: =SUMIF(Calendar!$A$2:$A$21,A3,Calendar!$W$2:$W$21) -> 0 | I3: =SUMIF(Calendar!$A$2:$A$21,A3,Calendar!$X$2:$X$21) -> 0 | J3: =SUMIF(Calendar!$A$2:$A$21,A3,Calendar!$Y$2:$Y$21) -> 0 | K3: =IFERROR(G3/E3*1000,0) -> 0
A4: 3 | B4: 46321 | C4: =COUNTIF(Calendar!$A$2:$A$21,A4) -> 4 | D4: =COUNTIFS(Calendar!$A$2:$A$21,A4,Calendar!$R$2:$R$21,"Posted") -> 0 | E4: =SUMIF(Calendar!$A$2:$A$21,A4,Calendar!$T$2:$T$21) -> 0 | F4: =SUMIF(Calendar!$A$2:$A$21,A4,Calendar!$U$2:$U$21) -> 0 | G4: =SUMIF(Calendar!$A$2:$A$21,A4,Calendar!$V$2:$V$21) -> 0 | H4: =SUMIF(Calendar!$A$2:$A$21,A4,Calendar!$W$2:$W$21) -> 0 | I4: =SUMIF(Calendar!$A$2:$A$21,A4,Calendar!$X$2:$X$21) -> 0 | J4: =SUMIF(Calendar!$A$2:$A$21,A4,Calendar!$Y$2:$Y$21) -> 0 | K4: =IFERROR(G4/E4*1000,0) -> 0
A5: 4 | B5: 46328 | C5: =COUNTIF(Calendar!$A$2:$A$21,A5) -> 4 | D5: =COUNTIFS(Calendar!$A$2:$A$21,A5,Calendar!$R$2:$R$21,"Posted") -> 0 | E5: =SUMIF(Calendar!$A$2:$A$21,A5,Calendar!$T$2:$T$21) -> 0 | F5: =SUMIF(Calendar!$A$2:$A$21,A5,Calendar!$U$2:$U$21) -> 0 | G5: =SUMIF(Calendar!$A$2:$A$21,A5,Calendar!$V$2:$V$21) -> 0 | H5: =SUMIF(Calendar!$A$2:$A$21,A5,Calendar!$W$2:$W$21) -> 0 | I5: =SUMIF(Calendar!$A$2:$A$21,A5,Calendar!$X$2:$X$21) -> 0 | J5: =SUMIF(Calendar!$A$2:$A$21,A5,Calendar!$Y$2:$Y$21) -> 0 | K5: =IFERROR(G5/E5*1000,0) -> 0
A6: 5 | B6: 46335 | C6: =COUNTIF(Calendar!$A$2:$A$21,A6) -> 4 | D6: =COUNTIFS(Calendar!$A$2:$A$21,A6,Calendar!$R$2:$R$21,"Posted") -> 0 | E6: =SUMIF(Calendar!$A$2:$A$21,A6,Calendar!$T$2:$T$21) -> 0 | F6: =SUMIF(Calendar!$A$2:$A$21,A6,Calendar!$U$2:$U$21) -> 0 | G6: =SUMIF(Calendar!$A$2:$A$21,A6,Calendar!$V$2:$V$21) -> 0 | H6: =SUMIF(Calendar!$A$2:$A$21,A6,Calendar!$W$2:$W$21) -> 0 | I6: =SUMIF(Calendar!$A$2:$A$21,A6,Calendar!$X$2:$X$21) -> 0 | J6: =SUMIF(Calendar!$A$2:$A$21,A6,Calendar!$Y$2:$Y$21) -> 0 | K6: =IFERROR(G6/E6*1000,0) -> 0
A7: Total | C7: =SUM(C2:C6) -> 20 | D7: =SUM(D2:D6) -> 0 | E7: =SUM(E2:E6) -> 0 | F7: =SUM(F2:F6) -> 0 | G7: =SUM(G2:G6) -> 0 | H7: =SUM(H2:H6) -> 0 | I7: =SUM(I2:I6) -> 0 | J7: =SUM(J2:J6) -> 0 | K7: =IFERROR(G7/E7*1000,0) -> 0
A9: Judge the account on calls booked and DMs, not reach. Shares per 1,000 reach is the best early signal of what Instagram will push.

Sheet Setup before 14 Oct
A1: Done? | B1: Task | C1: Why
B2: Switch to Business account, category Marketing Agency, contact email set | C2: Unlocks insights, contact button and approved DM tools
B3: Bio, name field and website link with UTM added | C3: Profile visits convert from here
B4: Two-factor authentication on, backup codes saved | C4: A hacked brand account is hard to recover
B5: Five lead magnets uploaded (Drive or website) with share links | C5: Every CTA keyword depends on these
B6: Auto-DM tool connected and the 7 keywords tested from a second account | C6: Broken DMs waste the first reels
B7: Highlight covers made: Teardowns, How we work, US/UK clients, COD/RTO, Book a call | C7: Profile looks complete from day one
B8: GA4 check that utm_source=instagram shows up | C8: So calls can be traced to reels
B9: Employment-contract check done | C9: Before posting anything publicly
B10: UK decision made (keep in bio and site, or remove) | C10: Bio and website must match
